{
    "configurations": [
        {
            "name": "Mac",
            "includePath": [
                "${workspaceFolder}/**",
                "/opt/homebrew/include",
                "/opt/homebrew/include/SDL2",
                "/Users/pestix/bin/emsdk/upstream/emscripten/system/include/"

            ],
            "defines": ["GDB_STUB_ENABLED", "__EMSCRIPTEN__"],
            "macFrameworkPath": [
                "/Applications/Xcode.app/Contents/Developer/Platforms/MacOSX.platform/Developer/SDKs/MacOSX.sdk/System/Library/Frameworks"
            ],
            "compilerPath": "/usr/bin/clang",
            "cStandard": "c17",
            "cppStandard": "c++17",
            "intelliSenseMode": "macos-clang-arm64",
            "configurationProvider": "ms-vscode.makefile-tools"
        }
    ],
    "version": 4
}
